autopycoin/__init__.py
autopycoin/_version.py
autopycoin/asserts.py
autopycoin/baseclass.py
autopycoin/baseclass_field.py
autopycoin/baseclass_field_test.py
autopycoin/baseclass_test.py
autopycoin/constant.py
autopycoin/extension_type.py
autopycoin/data/__init__.py
autopycoin/data/generate.py
autopycoin/data/generate_test.py
autopycoin/dataset/__init__.py
autopycoin/dataset/generator.py
autopycoin/dataset/generator_test.py
autopycoin/layers/__init__.py
autopycoin/layers/base_layer.py
autopycoin/layers/base_layer_test.py
autopycoin/layers/nbeats_layers.py
autopycoin/layers/nbeats_layers_test.py
autopycoin/losses/__init__.py
autopycoin/losses/losses.py
autopycoin/losses/losses_test.py
autopycoin/models/__init__.py
autopycoin/models/nbeats.py
autopycoin/models/nbeats_test.py
autopycoin/models/pool.py
autopycoin/models/training.py
autopycoin/models/training_test.py
autopycoin/test_utils/__init__.py
autopycoin/test_utils/testing_utils.py
autopycoin/utils/__init__.py
autopycoin/utils/data_utils.py
autopycoin/utils/data_utils_test.py
autopycoin-0.1.33.dist-info/LICENSE
autopycoin-0.1.33.dist-info/METADATA
autopycoin-0.1.33.dist-info/WHEEL
autopycoin-0.1.33.dist-info/top_level.txt
autopycoin-0.1.33.dist-info/RECORD
