Metadata-Version: 2.1
Name: autopycoin
Version: 0.1.33
Summary: Deep learning models for forecasting purposes.
Home-page: https://github.com/GaetanDu/autopycoin
Download-URL: https://github.com/GaetanDu/autopycoin
Maintainer: G. Dubuc
Maintainer-email: gaet.dub1@gmail.com
License: Apache license 2.0
Platform: UNKNOWN
Classifier: Intended Audience :: Science/Research
Classifier: Intended Audience :: Developers
Classifier: License :: OSI Approved
Classifier: Programming Language :: Python
Classifier: Topic :: Software Development
Classifier: Topic :: Scientific/Engineering
Classifier: Operating System :: Microsoft :: Windows
Classifier: Operating System :: POSIX
Classifier: Operating System :: Unix
Classifier: Operating System :: MacOS
Classifier: Programming Language :: Python :: 3.9
License-File: LICENSE
Requires-Dist: numpy
Requires-Dist: pandas
Requires-Dist: tensorflow (>=2.7.0)
Requires-Dist: tensorflow-probability
Requires-Dist: matplotlib
Provides-Extra: docs
Requires-Dist: sphinx ; extra == 'docs'
Requires-Dist: sphinx-gallery ; extra == 'docs'
Requires-Dist: sphinx-rtd-theme ; extra == 'docs'
Requires-Dist: numpydoc ; extra == 'docs'
Requires-Dist: matplotlib ; extra == 'docs'
Requires-Dist: pydata-sphinx-theme ; extra == 'docs'
Provides-Extra: tests
Requires-Dist: pytest ; extra == 'tests'
Requires-Dist: pytest-cov ; extra == 'tests'
